alephs/__init__.py
alephs/alephs.py
alephs/data/institutions.json
alephs-0.8.dist-info/METADATA
alephs-0.8.dist-info/WHEEL
alephs-0.8.dist-info/top_level.txt
alephs-0.8.dist-info/RECORD
