Metadata-Version: 2.1
Name: alephs
Version: 0.8
Summary: (A) (L)ist of (E)mergency (P)akistani (H)elp (S)ervices.
Author: siphr
Author-email: pypi@techtum.dev
Project-URL: Homepage, https://www.techtum.dev/work-alephs-220621.html
Project-URL: Source, https://github.com/siphr/alephs
Project-URL: Tracker, https://github.com/siphr/alephs/issues
Keywords: Pakistani,emergency,services,internet
Platform: any
